etb_pg/PG.py
etb_pg/__init__.py
etb_pg-0.1.6.dist-info/WHEEL
etb_pg-0.1.6.dist-info/METADATA
etb_pg-0.1.6.dist-info/RECORD
