Metadata-Version: 2.1
Name: etb-pg
Version: 0.1.6
Summary: Interface for PostgreSQL databases
Home-page: https://github.com/HFxLhT8JqeU5BnUG/etb-pg
License: MIT
Author: Tate Button
Author-email: yg3bpwn0or679hau8fxi@duck.com
Requires-Python: >=3.10,<4.0
Classifier: License :: OSI Approved :: MIT License
Classifier: Programming Language :: Python :: 3
Classifier: Programming Language :: Python :: 3.10
Requires-Dist: psycopg (>=3.1.18,<4.0.0)
Requires-Dist: psycopg-binary (>=3.1.18,<4.0.0)
Project-URL: Repository, https://github.com/HFxLhT8JqeU5BnUG/etb-pg
